gean/__init__.py
gean-0.0.11.dist-info/LICENSE
gean-0.0.11.dist-info/METADATA
gean-0.0.11.dist-info/WHEEL
gean-0.0.11.dist-info/top_level.txt
gean-0.0.11.dist-info/RECORD
