Metadata-Version: 2.1
Name: gean
Version: 0.0.11
Summary: A minimal IOC container inspired by Spring
Home-page: https://github.com/garciat/gean
Author: Gabriel Garcia
Author-email: me@garciat.com
License: UNKNOWN
Platform: UNKNOWN
Classifier: Programming Language :: Python :: 3
Classifier: License :: OSI Approved :: MIT License
Classifier: Operating System :: OS Independent
Requires-Python: >=3.6
